echidma/__init__.py
echidma/indexer_base.py
echidma/indexer_h5.py
echidma/indexer_memmap.py
echidma/caching/__init__.py
echidma/caching/chunk_cache.py
echidma/config_management/__init__.py
echidma/config_management/config_manager.py
echidma-0.0.4.dist-info/LICENSE
echidma-0.0.4.dist-info/METADATA
echidma-0.0.4.dist-info/WHEEL
echidma-0.0.4.dist-info/top_level.txt
echidma-0.0.4.dist-info/RECORD
